grappelli_menu/__init__.py
grappelli_menu/models.py
grappelli_menu/static/grappelli_menu/css/side-bar-menu.css
grappelli_menu/templates/admin/base.html
grappelli_menu/templatetags/__init__.py
grappelli_menu/templatetags/admin_apps.py
grappelli_side_menu-0.1.3.dist-info/DESCRIPTION.rst
grappelli_side_menu-0.1.3.dist-info/METADATA
grappelli_side_menu-0.1.3.dist-info/metadata.json
grappelli_side_menu-0.1.3.dist-info/RECORD
grappelli_side_menu-0.1.3.dist-info/top_level.txt
grappelli_side_menu-0.1.3.dist-info/WHEEL
