Metadata-Version: 2.0
Name: grappelli-side-menu
Version: 0.1.3
Summary: Side menu for Grappelli, the Django admin Interface
Home-page: https://github.com/dadoeyad/grappelli-side-menu
Author: Eyad Toma
Author-email: d.eyad.t@gmail.com
License: BSD
Keywords: grappelli-side-menu
Platform: UNKNOWN
Classifier: Development Status :: 2 - Pre-Alpha
Classifier: Framework :: Django
Classifier: Intended Audience :: Developers
Classifier: License :: OSI Approved :: BSD License
Classifier: Natural Language :: English
Classifier: Programming Language :: Python :: 2
Classifier: Programming Language :: Python :: 2.6
Classifier: Programming Language :: Python :: 2.7
Classifier: Programming Language :: Python :: 3
Classifier: Programming Language :: Python :: 3.3
